Metadata-Version: 1.1
Name: yifi
Version: 0.2.3
Summary: browse yifi on your command line
Home-page: https://github.com/AkhilMaskery/yifi
Author: vitaminC
Author-email: dmakhil@gmail.com
License: GPLv3
Keywords: yifi torrent download
Platform: UNKNOWN
Classifier: Development Status :: 4 - Beta
Classifier: Environment :: Console
Classifier: Intended Audience :: End Users/Desktop
Classifier: License :: OSI Approved :: GNU General Public License v3 (GPLv3)
Classifier: Operating System :: MacOS :: MacOS X
Classifier: Operating System :: Microsoft :: Windows
Classifier: Operating System :: POSIX
Classifier: Programming Language :: Python
Classifier: Topic :: Utilities
